[
  {
    "country": "Portugal",
    "city": "Lisbon",
    "cost_index": 55,
    "monthly_cost_usd": 1950,
    "rent_1br_city_center": 1200,
    "groceries_monthly": 250,
    "transport_monthly": 50,
    "utilities_monthly": 100,
    "internet_monthly": 30
  },
  {
    "country": "Portugal",
    "city": "Porto",
    "cost_index": 48,
    "monthly_cost_usd": 1650,
    "rent_1br_city_center": 950,
    "groceries_monthly": 230,
    "transport_monthly": 45,
    "utilities_monthly": 90,
    "internet_monthly": 28
  },
  {
    "country": "Spain",
    "city": "Barcelona",
    "cost_index": 62,
    "monthly_cost_usd": 2100,
    "rent_1br_city_center": 1350,
    "groceries_monthly": 280,
    "transport_monthly": 55,
    "utilities_monthly": 110,
    "internet_monthly": 32
  },
  {
    "country": "Spain",
    "city": "Madrid",
    "cost_index": 60,
    "monthly_cost_usd": 2050,
    "rent_1br_city_center": 1300,
    "groceries_monthly": 270,
    "transport_monthly": 52,
    "utilities_monthly": 108,
    "internet_monthly": 30
  },
  {
    "country": "Mexico",
    "city": "Mexico City",
    "cost_index": 38,
    "monthly_cost_usd": 1300,
    "rent_1br_city_center": 650,
    "groceries_monthly": 200,
    "transport_monthly": 35,
    "utilities_monthly": 75,
    "internet_monthly": 22
  },
  {
    "country": "Mexico",
    "city": "Playa del Carmen",
    "cost_index": 42,
    "monthly_cost_usd": 1450,
    "rent_1br_city_center": 800,
    "groceries_monthly": 220,
    "transport_monthly": 40,
    "utilities_monthly": 85,
    "internet_monthly": 25
  },
  {
    "country": "Thailand",
    "city": "Chiang Mai",
    "cost_index": 28,
    "monthly_cost_usd": 950,
    "rent_1br_city_center": 400,
    "groceries_monthly": 150,
    "transport_monthly": 30,
    "utilities_monthly": 60,
    "internet_monthly": 20
  },
  {
    "country": "Thailand",
    "city": "Bangkok",
    "cost_index": 35,
    "monthly_cost_usd": 1200,
    "rent_1br_city_center": 600,
    "groceries_monthly": 180,
    "transport_monthly": 40,
    "utilities_monthly": 70,
    "internet_monthly": 20
  },
  {
    "country": "Indonesia",
    "city": "Bali",
    "cost_index": 30,
    "monthly_cost_usd": 1050,
    "rent_1br_city_center": 500,
    "groceries_monthly": 160,
    "transport_monthly": 50,
    "utilities_monthly": 65,
    "internet_monthly": 22
  },
  {
    "country": "Colombia",
    "city": "Medellin",
    "cost_index": 32,
    "monthly_cost_usd": 1100,
    "rent_1br_city_center": 500,
    "groceries_monthly": 170,
    "transport_monthly": 30,
    "utilities_monthly": 60,
    "internet_monthly": 22
  },
  {
    "country": "Colombia",
    "city": "Bogota",
    "cost_index": 35,
    "monthly_cost_usd": 1200,
    "rent_1br_city_center": 600,
    "groceries_monthly": 180,
    "transport_monthly": 35,
    "utilities_monthly": 65,
    "internet_monthly": 22
  },
  {
    "country": "Georgia",
    "city": "Tbilisi",
    "cost_index": 30,
    "monthly_cost_usd": 1050,
    "rent_1br_city_center": 500,
    "groceries_monthly": 150,
    "transport_monthly": 25,
    "utilities_monthly": 55,
    "internet_monthly": 18
  },
  {
    "country": "Romania",
    "city": "Bucharest",
    "cost_index": 38,
    "monthly_cost_usd": 1300,
    "rent_1br_city_center": 600,
    "groceries_monthly": 200,
    "transport_monthly": 35,
    "utilities_monthly": 80,
    "internet_monthly": 15
  },
  {
    "country": "Czech Republic",
    "city": "Prague",
    "cost_index": 52,
    "monthly_cost_usd": 1800,
    "rent_1br_city_center": 1000,
    "groceries_monthly": 250,
    "transport_monthly": 45,
    "utilities_monthly": 95,
    "internet_monthly": 20
  },
  {
    "country": "Hungary",
    "city": "Budapest",
    "cost_index": 43,
    "monthly_cost_usd": 1450,
    "rent_1br_city_center": 750,
    "groceries_monthly": 210,
    "transport_monthly": 40,
    "utilities_monthly": 85,
    "internet_monthly": 18
  },
  {
    "country": "Poland",
    "city": "Krakow",
    "cost_index": 40,
    "monthly_cost_usd": 1350,
    "rent_1br_city_center": 700,
    "groceries_monthly": 200,
    "transport_monthly": 35,
    "utilities_monthly": 80,
    "internet_monthly": 18
  },
  {
    "country": "Poland",
    "city": "Warsaw",
    "cost_index": 45,
    "monthly_cost_usd": 1550,
    "rent_1br_city_center": 900,
    "groceries_monthly": 220,
    "transport_monthly": 40,
    "utilities_monthly": 90,
    "internet_monthly": 18
  },
  {
    "country": "Estonia",
    "city": "Tallinn",
    "cost_index": 55,
    "monthly_cost_usd": 1900,
    "rent_1br_city_center": 1050,
    "groceries_monthly": 250,
    "transport_monthly": 45,
    "utilities_monthly": 100,
    "internet_monthly": 22
  },
  {
    "country": "Croatia",
    "city": "Split",
    "cost_index": 48,
    "monthly_cost_usd": 1650,
    "rent_1br_city_center": 900,
    "groceries_monthly": 230,
    "transport_monthly": 40,
    "utilities_monthly": 90,
    "internet_monthly": 25
  },
  {
    "country": "Croatia",
    "city": "Zagreb",
    "cost_index": 50,
    "monthly_cost_usd": 1700,
    "rent_1br_city_center": 950,
    "groceries_monthly": 240,
    "transport_monthly": 42,
    "utilities_monthly": 95,
    "internet_monthly": 25
  },
  {
    "country": "Malta",
    "city": "Valletta",
    "cost_index": 62,
    "monthly_cost_usd": 2100,
    "rent_1br_city_center": 1200,
    "groceries_monthly": 280,
    "transport_monthly": 30,
    "utilities_monthly": 110,
    "internet_monthly": 30
  },
  {
    "country": "UAE",
    "city": "Dubai",
    "cost_index": 82,
    "monthly_cost_usd": 2800,
    "rent_1br_city_center": 1800,
    "groceries_monthly": 350,
    "transport_monthly": 120,
    "utilities_monthly": 150,
    "internet_monthly": 80
  },
  {
    "country": "Singapore",
    "city": "Singapore",
    "cost_index": 95,
    "monthly_cost_usd": 3200,
    "rent_1br_city_center": 2200,
    "groceries_monthly": 400,
    "transport_monthly": 100,
    "utilities_monthly": 130,
    "internet_monthly": 35
  },
  {
    "country": "Japan",
    "city": "Tokyo",
    "cost_index": 75,
    "monthly_cost_usd": 2550,
    "rent_1br_city_center": 1400,
    "groceries_monthly": 350,
    "transport_monthly": 90,
    "utilities_monthly": 120,
    "internet_monthly": 35
  },
  {
    "country": "South Korea",
    "city": "Seoul",
    "cost_index": 72,
    "monthly_cost_usd": 2450,
    "rent_1br_city_center": 1350,
    "groceries_monthly": 320,
    "transport_monthly": 80,
    "utilities_monthly": 115,
    "internet_monthly": 30
  },
  {
    "country": "Taiwan",
    "city": "Taipei",
    "cost_index": 60,
    "monthly_cost_usd": 2050,
    "rent_1br_city_center": 950,
    "groceries_monthly": 280,
    "transport_monthly": 55,
    "utilities_monthly": 105,
    "internet_monthly": 28
  },
  {
    "country": "Argentina",
    "city": "Buenos Aires",
    "cost_index": 32,
    "monthly_cost_usd": 1100,
    "rent_1br_city_center": 500,
    "groceries_monthly": 200,
    "transport_monthly": 30,
    "utilities_monthly": 60,
    "internet_monthly": 18
  },
  {
    "country": "Brazil",
    "city": "Florianopolis",
    "cost_index": 40,
    "monthly_cost_usd": 1350,
    "rent_1br_city_center": 650,
    "groceries_monthly": 220,
    "transport_monthly": 45,
    "utilities_monthly": 80,
    "internet_monthly": 22
  },
  {
    "country": "Greece",
    "city": "Athens",
    "cost_index": 52,
    "monthly_cost_usd": 1800,
    "rent_1br_city_center": 900,
    "groceries_monthly": 260,
    "transport_monthly": 50,
    "utilities_monthly": 100,
    "internet_monthly": 28
  },
  {
    "country": "Greece",
    "city": "Thessaloniki",
    "cost_index": 45,
    "monthly_cost_usd": 1550,
    "rent_1br_city_center": 750,
    "groceries_monthly": 240,
    "transport_monthly": 45,
    "utilities_monthly": 90,
    "internet_monthly": 25
  },
  {
    "country": "Italy",
    "city": "Palermo",
    "cost_index": 48,
    "monthly_cost_usd": 1650,
    "rent_1br_city_center": 750,
    "groceries_monthly": 250,
    "transport_monthly": 40,
    "utilities_monthly": 95,
    "internet_monthly": 28
  },
  {
    "country": "Italy",
    "city": "Naples",
    "cost_index": 50,
    "monthly_cost_usd": 1700,
    "rent_1br_city_center": 800,
    "groceries_monthly": 260,
    "transport_monthly": 42,
    "utilities_monthly": 98,
    "internet_monthly": 28
  },
  {
    "country": "Montenegro",
    "city": "Kotor",
    "cost_index": 42,
    "monthly_cost_usd": 1450,
    "rent_1br_city_center": 700,
    "groceries_monthly": 220,
    "transport_monthly": 35,
    "utilities_monthly": 80,
    "internet_monthly": 22
  },
  {
    "country": "Serbia",
    "city": "Belgrade",
    "cost_index": 35,
    "monthly_cost_usd": 1200,
    "rent_1br_city_center": 550,
    "groceries_monthly": 190,
    "transport_monthly": 35,
    "utilities_monthly": 75,
    "internet_monthly": 18
  },
  {
    "country": "Albania",
    "city": "Tirana",
    "cost_index": 30,
    "monthly_cost_usd": 1050,
    "rent_1br_city_center": 450,
    "groceries_monthly": 170,
    "transport_monthly": 30,
    "utilities_monthly": 65,
    "internet_monthly": 15
  },
  {
    "country": "Philippines",
    "city": "Cebu",
    "cost_index": 28,
    "monthly_cost_usd": 950,
    "rent_1br_city_center": 400,
    "groceries_monthly": 160,
    "transport_monthly": 35,
    "utilities_monthly": 60,
    "internet_monthly": 20
  },
  {
    "country": "Philippines",
    "city": "Manila",
    "cost_index": 32,
    "monthly_cost_usd": 1100,
    "rent_1br_city_center": 550,
    "groceries_monthly": 175,
    "transport_monthly": 40,
    "utilities_monthly": 65,
    "internet_monthly": 20
  },
  {
    "country": "Vietnam",
    "city": "Ho Chi Minh City",
    "cost_index": 30,
    "monthly_cost_usd": 1050,
    "rent_1br_city_center": 500,
    "groceries_monthly": 160,
    "transport_monthly": 30,
    "utilities_monthly": 60,
    "internet_monthly": 15
  },
  {
    "country": "Vietnam",
    "city": "Da Nang",
    "cost_index": 25,
    "monthly_cost_usd": 850,
    "rent_1br_city_center": 350,
    "groceries_monthly": 140,
    "transport_monthly": 25,
    "utilities_monthly": 50,
    "internet_monthly": 15
  },
  {
    "country": "Costa Rica",
    "city": "San Jose",
    "cost_index": 45,
    "monthly_cost_usd": 1550,
    "rent_1br_city_center": 750,
    "groceries_monthly": 240,
    "transport_monthly": 45,
    "utilities_monthly": 90,
    "internet_monthly": 35
  },
  {
    "country": "Panama",
    "city": "Panama City",
    "cost_index": 48,
    "monthly_cost_usd": 1650,
    "rent_1br_city_center": 850,
    "groceries_monthly": 250,
    "transport_monthly": 50,
    "utilities_monthly": 95,
    "internet_monthly": 40
  },
  {
    "country": "United States",
    "city": "Austin",
    "cost_index": 100,
    "monthly_cost_usd": 3500,
    "rent_1br_city_center": 1800,
    "groceries_monthly": 450,
    "transport_monthly": 120,
    "utilities_monthly": 150,
    "internet_monthly": 60
  },
  {
    "country": "United States",
    "city": "San Francisco",
    "cost_index": 145,
    "monthly_cost_usd": 5100,
    "rent_1br_city_center": 3200,
    "groceries_monthly": 600,
    "transport_monthly": 120,
    "utilities_monthly": 180,
    "internet_monthly": 70
  },
  {
    "country": "United States",
    "city": "New York",
    "cost_index": 140,
    "monthly_cost_usd": 4900,
    "rent_1br_city_center": 3000,
    "groceries_monthly": 580,
    "transport_monthly": 130,
    "utilities_monthly": 175,
    "internet_monthly": 70
  }
]
